LICENSE
README.md
setup.py
samap/__init__.py
samap/analysis.py
samap/mapping.py
samap/utils.py
samap.egg-info/PKG-INFO
samap.egg-info/SOURCES.txt
samap.egg-info/dependency_links.txt
samap.egg-info/not-zip-safe
samap.egg-info/requires.txt
samap.egg-info/top_level.txt