Metadata-Version: 2.1
Name: samap
Version: 1.0.3
Summary: The SAMap algorithm
Home-page: https://github.com/atarashansky/SAMap
Author: Alexander J. Tarashansky
Author-email: tarashan@stanford.edu
License: UNKNOWN
Keywords: scrnaseq analysis manifold reconstruction cross-species mapping
Platform: UNKNOWN
Requires-Python: >=3.7
License-File: LICENSE
